{
  "jobs": [
    {
      "type": "gen",
      "wallet": "lab_legacy_a0",
      "network": "bitcoin",
      "witness": "legacy",
      "account": 0,
      "branch": "both",
      "start": 0,
      "count": 10,
      "precreate": 10,
      "out_dir": "./mass_exports/bitcoin/legacy/a0",
      "format": "csv,jsonl",
      "xpub_file": "./mass_exports/xpubs/bitcoin/legacy/a0.xpub"
    },
    {
      "type": "verify",
      "wallet": "lab_legacy_a0",
      "xpub_file": "./mass_exports/xpubs/bitcoin/legacy/a0.xpub",
      "network": "bitcoin",
      "witness": "legacy",
      "branch": "receive",
      "start": 0,
      "count": 10,
      "compare_from_latest_gen": true
    },
    {
      "type": "verify",
      "wallet": "lab_legacy_a0",
      "xpub_file": "./mass_exports/xpubs/bitcoin/legacy/a0.xpub",
      "network": "bitcoin",
      "witness": "legacy",
      "branch": "change",
      "start": 0,
      "count": 10,
      "compare_from_latest_gen": true
    },
    {
      "type": "gen",
      "wallet": "lab_legacy_a1",
      "network": "bitcoin",
      "witness": "legacy",
      "account": 1,
      "branch": "both",
      "start": 0,
      "count": 5,
      "precreate": 5,
      "out_dir": "./mass_exports/bitcoin/legacy/a1",
      "format": "csv,jsonl",
      "xpub_file": "./mass_exports/xpubs/bitcoin/legacy/a1.xpub"
    },
    {
      "type": "verify",
      "wallet": "lab_legacy_a1",
      "xpub_file": "./mass_exports/xpubs/bitcoin/legacy/a1.xpub",
      "network": "bitcoin",
      "witness": "legacy",
      "branch": "receive",
      "start": 0,
      "count": 5,
      "compare_from_latest_gen": true
    },
    {
      "type": "verify",
      "wallet": "lab_legacy_a1",
      "xpub_file": "./mass_exports/xpubs/bitcoin/legacy/a1.xpub",
      "network": "bitcoin",
      "witness": "legacy",
      "branch": "change",
      "start": 0,
      "count": 5,
      "compare_from_latest_gen": true
    },
    {
      "type": "gen",
      "wallet": "lab_p2sh-segwit_a0",
      "network": "bitcoin",
      "witness": "p2sh-segwit",
      "account": 0,
      "branch": "both",
      "start": 0,
      "count": 10,
      "precreate": 10,
      "out_dir": "./mass_exports/bitcoin/p2sh-segwit/a0",
      "format": "csv,jsonl",
      "xpub_file": "./mass_exports/xpubs/bitcoin/p2sh-segwit/a0.xpub"
    },
    {
      "type": "verify",
      "wallet": "lab_p2sh-segwit_a0",
      "xpub_file": "./mass_exports/xpubs/bitcoin/p2sh-segwit/a0.xpub",
      "network": "bitcoin",
      "witness": "p2sh-segwit",
      "branch": "receive",
      "start": 0,
      "count": 10,
      "compare_from_latest_gen": true
    },
    {
      "type": "verify",
      "wallet": "lab_p2sh-segwit_a0",
      "xpub_file": "./mass_exports/xpubs/bitcoin/p2sh-segwit/a0.xpub",
      "network": "bitcoin",
      "witness": "p2sh-segwit",
      "branch": "change",
      "start": 0,
      "count": 10,
      "compare_from_latest_gen": true
    },
    {
      "type": "gen",
      "wallet": "lab_p2sh-segwit_a1",
      "network": "bitcoin",
      "witness": "p2sh-segwit",
      "account": 1,
      "branch": "both",
      "start": 0,
      "count": 5,
      "precreate": 5,
      "out_dir": "./mass_exports/bitcoin/p2sh-segwit/a1",
      "format": "csv,jsonl",
      "xpub_file": "./mass_exports/xpubs/bitcoin/p2sh-segwit/a1.xpub"
    },
    {
      "type": "verify",
      "wallet": "lab_p2sh-segwit_a1",
      "xpub_file": "./mass_exports/xpubs/bitcoin/p2sh-segwit/a1.xpub",
      "network": "bitcoin",
      "witness": "p2sh-segwit",
      "branch": "receive",
      "start": 0,
      "count": 5,
      "compare_from_latest_gen": true
    },
    {
      "type": "verify",
      "wallet": "lab_p2sh-segwit_a1",
      "xpub_file": "./mass_exports/xpubs/bitcoin/p2sh-segwit/a1.xpub",
      "network": "bitcoin",
      "witness": "p2sh-segwit",
      "branch": "change",
      "start": 0,
      "count": 5,
      "compare_from_latest_gen": true
    },
    {
      "type": "gen",
      "wallet": "lab_segwit_a0",
      "network": "bitcoin",
      "witness": "segwit",
      "account": 0,
      "branch": "both",
      "start": 0,
      "count": 10,
      "precreate": 10,
      "out_dir": "./mass_exports/bitcoin/segwit/a0",
      "format": "csv,jsonl",
      "xpub_file": "./mass_exports/xpubs/bitcoin/segwit/a0.xpub"
    },
    {
      "type": "verify",
      "wallet": "lab_segwit_a0",
      "xpub_file": "./mass_exports/xpubs/bitcoin/segwit/a0.xpub",
      "network": "bitcoin",
      "witness": "segwit",
      "branch": "receive",
      "start": 0,
      "count": 10,
      "compare_from_latest_gen": true
    },
    {
      "type": "verify",
      "wallet": "lab_segwit_a0",
      "xpub_file": "./mass_exports/xpubs/bitcoin/segwit/a0.xpub",
      "network": "bitcoin",
      "witness": "segwit",
      "branch": "change",
      "start": 0,
      "count": 10,
      "compare_from_latest_gen": true
    },
    {
      "type": "gen",
      "wallet": "lab_segwit_a1",
      "network": "bitcoin",
      "witness": "segwit",
      "account": 1,
      "branch": "both",
      "start": 0,
      "count": 5,
      "precreate": 5,
      "out_dir": "./mass_exports/bitcoin/segwit/a1",
      "format": "csv,jsonl",
      "xpub_file": "./mass_exports/xpubs/bitcoin/segwit/a1.xpub"
    },
    {
      "type": "verify",
      "wallet": "lab_segwit_a1",
      "xpub_file": "./mass_exports/xpubs/bitcoin/segwit/a1.xpub",
      "network": "bitcoin",
      "witness": "segwit",
      "branch": "receive",
      "start": 0,
      "count": 5,
      "compare_from_latest_gen": true
    },
    {
      "type": "verify",
      "wallet": "lab_segwit_a1",
      "xpub_file": "./mass_exports/xpubs/bitcoin/segwit/a1.xpub",
      "network": "bitcoin",
      "witness": "segwit",
      "branch": "change",
      "start": 0,
      "count": 5,
      "compare_from_latest_gen": true
    },
    {
      "type": "gen",
      "wallet": "lab_tr_a0",
      "network": "bitcoin",
      "witness": "tr",
      "account": 0,
      "branch": "both",
      "start": 0,
      "count": 10,
      "precreate": 10,
      "out_dir": "./mass_exports/bitcoin/tr/a0",
      "format": "csv,jsonl",
      "xpub_file": "./mass_exports/xpubs/bitcoin/tr/a0.xpub"
    },
    {
      "type": "verify",
      "wallet": "lab_tr_a0",
      "xpub_file": "./mass_exports/xpubs/bitcoin/tr/a0.xpub",
      "network": "bitcoin",
      "witness": "tr",
      "branch": "receive",
      "start": 0,
      "count": 10,
      "compare_from_latest_gen": true
    },
    {
      "type": "verify",
      "wallet": "lab_tr_a0",
      "xpub_file": "./mass_exports/xpubs/bitcoin/tr/a0.xpub",
      "network": "bitcoin",
      "witness": "tr",
      "branch": "change",
      "start": 0,
      "count": 10,
      "compare_from_latest_gen": true
    },
    {
      "type": "gen",
      "wallet": "lab_tr_a1",
      "network": "bitcoin",
      "witness": "tr",
      "account": 1,
      "branch": "both",
      "start": 0,
      "count": 5,
      "precreate": 5,
      "out_dir": "./mass_exports/bitcoin/tr/a1",
      "format": "csv,jsonl",
      "xpub_file": "./mass_exports/xpubs/bitcoin/tr/a1.xpub"
    },
    {
      "type": "verify",
      "wallet": "lab_tr_a1",
      "xpub_file": "./mass_exports/xpubs/bitcoin/tr/a1.xpub",
      "network": "bitcoin",
      "witness": "tr",
      "branch": "receive",
      "start": 0,
      "count": 5,
      "compare_from_latest_gen": true
    },
    {
      "type": "verify",
      "wallet": "lab_tr_a1",
      "xpub_file": "./mass_exports/xpubs/bitcoin/tr/a1.xpub",
      "network": "bitcoin",
      "witness": "tr",
      "branch": "change",
      "start": 0,
      "count": 5,
      "compare_from_latest_gen": true
    },
    {
      "type": "gen",
      "wallet": "lab_legacy_a0",
      "network": "testnet",
      "witness": "legacy",
      "account": 0,
      "branch": "both",
      "start": 0,
      "count": 10,
      "precreate": 10,
      "out_dir": "./mass_exports/testnet/legacy/a0",
      "format": "csv,jsonl",
      "xpub_file": "./mass_exports/xpubs/testnet/legacy/a0.xpub"
    },
    {
      "type": "verify",
      "wallet": "lab_legacy_a0",
      "xpub_file": "./mass_exports/xpubs/testnet/legacy/a0.xpub",
      "network": "testnet",
      "witness": "legacy",
      "branch": "receive",
      "start": 0,
      "count": 10,
      "compare_from_latest_gen": true
    },
    {
      "type": "verify",
      "wallet": "lab_legacy_a0",
      "xpub_file": "./mass_exports/xpubs/testnet/legacy/a0.xpub",
      "network": "testnet",
      "witness": "legacy",
      "branch": "change",
      "start": 0,
      "count": 10,
      "compare_from_latest_gen": true
    },
    {
      "type": "gen",
      "wallet": "lab_legacy_a1",
      "network": "testnet",
      "witness": "legacy",
      "account": 1,
      "branch": "both",
      "start": 0,
      "count": 5,
      "precreate": 5,
      "out_dir": "./mass_exports/testnet/legacy/a1",
      "format": "csv,jsonl",
      "xpub_file": "./mass_exports/xpubs/testnet/legacy/a1.xpub"
    },
    {
      "type": "verify",
      "wallet": "lab_legacy_a1",
      "xpub_file": "./mass_exports/xpubs/testnet/legacy/a1.xpub",
      "network": "testnet",
      "witness": "legacy",
      "branch": "receive",
      "start": 0,
      "count": 5,
      "compare_from_latest_gen": true
    },
    {
      "type": "verify",
      "wallet": "lab_legacy_a1",
      "xpub_file": "./mass_exports/xpubs/testnet/legacy/a1.xpub",
      "network": "testnet",
      "witness": "legacy",
      "branch": "change",
      "start": 0,
      "count": 5,
      "compare_from_latest_gen": true
    },
    {
      "type": "gen",
      "wallet": "lab_p2sh-segwit_a0",
      "network": "testnet",
      "witness": "p2sh-segwit",
      "account": 0,
      "branch": "both",
      "start": 0,
      "count": 10,
      "precreate": 10,
      "out_dir": "./mass_exports/testnet/p2sh-segwit/a0",
      "format": "csv,jsonl",
      "xpub_file": "./mass_exports/xpubs/testnet/p2sh-segwit/a0.xpub"
    },
    {
      "type": "verify",
      "wallet": "lab_p2sh-segwit_a0",
      "xpub_file": "./mass_exports/xpubs/testnet/p2sh-segwit/a0.xpub",
      "network": "testnet",
      "witness": "p2sh-segwit",
      "branch": "receive",
      "start": 0,
      "count": 10,
      "compare_from_latest_gen": true
    },
    {
      "type": "verify",
      "wallet": "lab_p2sh-segwit_a0",
      "xpub_file": "./mass_exports/xpubs/testnet/p2sh-segwit/a0.xpub",
      "network": "testnet",
      "witness": "p2sh-segwit",
      "branch": "change",
      "start": 0,
      "count": 10,
      "compare_from_latest_gen": true
    },
    {
      "type": "gen",
      "wallet": "lab_p2sh-segwit_a1",
      "network": "testnet",
      "witness": "p2sh-segwit",
      "account": 1,
      "branch": "both",
      "start": 0,
      "count": 5,
      "precreate": 5,
      "out_dir": "./mass_exports/testnet/p2sh-segwit/a1",
      "format": "csv,jsonl",
      "xpub_file": "./mass_exports/xpubs/testnet/p2sh-segwit/a1.xpub"
    },
    {
      "type": "verify",
      "wallet": "lab_p2sh-segwit_a1",
      "xpub_file": "./mass_exports/xpubs/testnet/p2sh-segwit/a1.xpub",
      "network": "testnet",
      "witness": "p2sh-segwit",
      "branch": "receive",
      "start": 0,
      "count": 5,
      "compare_from_latest_gen": true
    },
    {
      "type": "verify",
      "wallet": "lab_p2sh-segwit_a1",
      "xpub_file": "./mass_exports/xpubs/testnet/p2sh-segwit/a1.xpub",
      "network": "testnet",
      "witness": "p2sh-segwit",
      "branch": "change",
      "start": 0,
      "count": 5,
      "compare_from_latest_gen": true
    },
    {
      "type": "gen",
      "wallet": "lab_segwit_a0",
      "network": "testnet",
      "witness": "segwit",
      "account": 0,
      "branch": "both",
      "start": 0,
      "count": 10,
      "precreate": 10,
      "out_dir": "./mass_exports/testnet/segwit/a0",
      "format": "csv,jsonl",
      "xpub_file": "./mass_exports/xpubs/testnet/segwit/a0.xpub"
    },
    {
      "type": "verify",
      "wallet": "lab_segwit_a0",
      "xpub_file": "./mass_exports/xpubs/testnet/segwit/a0.xpub",
      "network": "testnet",
      "witness": "segwit",
      "branch": "receive",
      "start": 0,
      "count": 10,
      "compare_from_latest_gen": true
    },
    {
      "type": "verify",
      "wallet": "lab_segwit_a0",
      "xpub_file": "./mass_exports/xpubs/testnet/segwit/a0.xpub",
      "network": "testnet",
      "witness": "segwit",
      "branch": "change",
      "start": 0,
      "count": 10,
      "compare_from_latest_gen": true
    },
    {
      "type": "gen",
      "wallet": "lab_segwit_a1",
      "network": "testnet",
      "witness": "segwit",
      "account": 1,
      "branch": "both",
      "start": 0,
      "count": 5,
      "precreate": 5,
      "out_dir": "./mass_exports/testnet/segwit/a1",
      "format": "csv,jsonl",
      "xpub_file": "./mass_exports/xpubs/testnet/segwit/a1.xpub"
    },
    {
      "type": "verify",
      "wallet": "lab_segwit_a1",
      "xpub_file": "./mass_exports/xpubs/testnet/segwit/a1.xpub",
      "network": "testnet",
      "witness": "segwit",
      "branch": "receive",
      "start": 0,
      "count": 5,
      "compare_from_latest_gen": true
    },
    {
      "type": "verify",
      "wallet": "lab_segwit_a1",
      "xpub_file": "./mass_exports/xpubs/testnet/segwit/a1.xpub",
      "network": "testnet",
      "witness": "segwit",
      "branch": "change",
      "start": 0,
      "count": 5,
      "compare_from_latest_gen": true
    },
    {
      "type": "gen",
      "wallet": "lab_tr_a0",
      "network": "testnet",
      "witness": "tr",
      "account": 0,
      "branch": "both",
      "start": 0,
      "count": 10,
      "precreate": 10,
      "out_dir": "./mass_exports/testnet/tr/a0",
      "format": "csv,jsonl",
      "xpub_file": "./mass_exports/xpubs/testnet/tr/a0.xpub"
    },
    {
      "type": "verify",
      "wallet": "lab_tr_a0",
      "xpub_file": "./mass_exports/xpubs/testnet/tr/a0.xpub",
      "network": "testnet",
      "witness": "tr",
      "branch": "receive",
      "start": 0,
      "count": 10,
      "compare_from_latest_gen": true
    },
    {
      "type": "verify",
      "wallet": "lab_tr_a0",
      "xpub_file": "./mass_exports/xpubs/testnet/tr/a0.xpub",
      "network": "testnet",
      "witness": "tr",
      "branch": "change",
      "start": 0,
      "count": 10,
      "compare_from_latest_gen": true
    },
    {
      "type": "gen",
      "wallet": "lab_tr_a1",
      "network": "testnet",
      "witness": "tr",
      "account": 1,
      "branch": "both",
      "start": 0,
      "count": 5,
      "precreate": 5,
      "out_dir": "./mass_exports/testnet/tr/a1",
      "format": "csv,jsonl",
      "xpub_file": "./mass_exports/xpubs/testnet/tr/a1.xpub"
    },
    {
      "type": "verify",
      "wallet": "lab_tr_a1",
      "xpub_file": "./mass_exports/xpubs/testnet/tr/a1.xpub",
      "network": "testnet",
      "witness": "tr",
      "branch": "receive",
      "start": 0,
      "count": 5,
      "compare_from_latest_gen": true
    },
    {
      "type": "verify",
      "wallet": "lab_tr_a1",
      "xpub_file": "./mass_exports/xpubs/testnet/tr/a1.xpub",
      "network": "testnet",
      "witness": "tr",
      "branch": "change",
      "start": 0,
      "count": 5,
      "compare_from_latest_gen": true
    },
    {
      "type": "gen",
      "wallet": "lab_legacy_a0",
      "network": "regtest",
      "witness": "legacy",
      "account": 0,
      "branch": "both",
      "start": 0,
      "count": 10,
      "precreate": 10,
      "out_dir": "./mass_exports/regtest/legacy/a0",
      "format": "csv,jsonl",
      "xpub_file": "./mass_exports/xpubs/regtest/legacy/a0.xpub"
    },
    {
      "type": "verify",
      "wallet": "lab_legacy_a0",
      "xpub_file": "./mass_exports/xpubs/regtest/legacy/a0.xpub",
      "network": "regtest",
      "witness": "legacy",
      "branch": "receive",
      "start": 0,
      "count": 10,
      "compare_from_latest_gen": true
    },
    {
      "type": "verify",
      "wallet": "lab_legacy_a0",
      "xpub_file": "./mass_exports/xpubs/regtest/legacy/a0.xpub",
      "network": "regtest",
      "witness": "legacy",
      "branch": "change",
      "start": 0,
      "count": 10,
      "compare_from_latest_gen": true
    },
    {
      "type": "gen",
      "wallet": "lab_legacy_a1",
      "network": "regtest",
      "witness": "legacy",
      "account": 1,
      "branch": "both",
      "start": 0,
      "count": 5,
      "precreate": 5,
      "out_dir": "./mass_exports/regtest/legacy/a1",
      "format": "csv,jsonl",
      "xpub_file": "./mass_exports/xpubs/regtest/legacy/a1.xpub"
    },
    {
      "type": "verify",
      "wallet": "lab_legacy_a1",
      "xpub_file": "./mass_exports/xpubs/regtest/legacy/a1.xpub",
      "network": "regtest",
      "witness": "legacy",
      "branch": "receive",
      "start": 0,
      "count": 5,
      "compare_from_latest_gen": true
    },
    {
      "type": "verify",
      "wallet": "lab_legacy_a1",
      "xpub_file": "./mass_exports/xpubs/regtest/legacy/a1.xpub",
      "network": "regtest",
      "witness": "legacy",
      "branch": "change",
      "start": 0,
      "count": 5,
      "compare_from_latest_gen": true
    },
    {
      "type": "gen",
      "wallet": "lab_p2sh-segwit_a0",
      "network": "regtest",
      "witness": "p2sh-segwit",
      "account": 0,
      "branch": "both",
      "start": 0,
      "count": 10,
      "precreate": 10,
      "out_dir": "./mass_exports/regtest/p2sh-segwit/a0",
      "format": "csv,jsonl",
      "xpub_file": "./mass_exports/xpubs/regtest/p2sh-segwit/a0.xpub"
    },
    {
      "type": "verify",
      "wallet": "lab_p2sh-segwit_a0",
      "xpub_file": "./mass_exports/xpubs/regtest/p2sh-segwit/a0.xpub",
      "network": "regtest",
      "witness": "p2sh-segwit",
      "branch": "receive",
      "start": 0,
      "count": 10,
      "compare_from_latest_gen": true
    },
    {
      "type": "verify",
      "wallet": "lab_p2sh-segwit_a0",
      "xpub_file": "./mass_exports/xpubs/regtest/p2sh-segwit/a0.xpub",
      "network": "regtest",
      "witness": "p2sh-segwit",
      "branch": "change",
      "start": 0,
      "count": 10,
      "compare_from_latest_gen": true
    },
    {
      "type": "gen",
      "wallet": "lab_p2sh-segwit_a1",
      "network": "regtest",
      "witness": "p2sh-segwit",
      "account": 1,
      "branch": "both",
      "start": 0,
      "count": 5,
      "precreate": 5,
      "out_dir": "./mass_exports/regtest/p2sh-segwit/a1",
      "format": "csv,jsonl",
      "xpub_file": "./mass_exports/xpubs/regtest/p2sh-segwit/a1.xpub"
    },
    {
      "type": "verify",
      "wallet": "lab_p2sh-segwit_a1",
      "xpub_file": "./mass_exports/xpubs/regtest/p2sh-segwit/a1.xpub",
      "network": "regtest",
      "witness": "p2sh-segwit",
      "branch": "receive",
      "start": 0,
      "count": 5,
      "compare_from_latest_gen": true
    },
    {
      "type": "verify",
      "wallet": "lab_p2sh-segwit_a1",
      "xpub_file": "./mass_exports/xpubs/regtest/p2sh-segwit/a1.xpub",
      "network": "regtest",
      "witness": "p2sh-segwit",
      "branch": "change",
      "start": 0,
      "count": 5,
      "compare_from_latest_gen": true
    },
    {
      "type": "gen",
      "wallet": "lab_segwit_a0",
      "network": "regtest",
      "witness": "segwit",
      "account": 0,
      "branch": "both",
      "start": 0,
      "count": 10,
      "precreate": 10,
      "out_dir": "./mass_exports/regtest/segwit/a0",
      "format": "csv,jsonl",
      "xpub_file": "./mass_exports/xpubs/regtest/segwit/a0.xpub"
    },
    {
      "type": "verify",
      "wallet": "lab_segwit_a0",
      "xpub_file": "./mass_exports/xpubs/regtest/segwit/a0.xpub",
      "network": "regtest",
      "witness": "segwit",
      "branch": "receive",
      "start": 0,
      "count": 10,
      "compare_from_latest_gen": true
    },
    {
      "type": "verify",
      "wallet": "lab_segwit_a0",
      "xpub_file": "./mass_exports/xpubs/regtest/segwit/a0.xpub",
      "network": "regtest",
      "witness": "segwit",
      "branch": "change",
      "start": 0,
      "count": 10,
      "compare_from_latest_gen": true
    },
    {
      "type": "gen",
      "wallet": "lab_segwit_a1",
      "network": "regtest",
      "witness": "segwit",
      "account": 1,
      "branch": "both",
      "start": 0,
      "count": 5,
      "precreate": 5,
      "out_dir": "./mass_exports/regtest/segwit/a1",
      "format": "csv,jsonl",
      "xpub_file": "./mass_exports/xpubs/regtest/segwit/a1.xpub"
    },
    {
      "type": "verify",
      "wallet": "lab_segwit_a1",
      "xpub_file": "./mass_exports/xpubs/regtest/segwit/a1.xpub",
      "network": "regtest",
      "witness": "segwit",
      "branch": "receive",
      "start": 0,
      "count": 5,
      "compare_from_latest_gen": true
    },
    {
      "type": "verify",
      "wallet": "lab_segwit_a1",
      "xpub_file": "./mass_exports/xpubs/regtest/segwit/a1.xpub",
      "network": "regtest",
      "witness": "segwit",
      "branch": "change",
      "start": 0,
      "count": 5,
      "compare_from_latest_gen": true
    },
    {
      "type": "gen",
      "wallet": "lab_tr_a0",
      "network": "regtest",
      "witness": "tr",
      "account": 0,
      "branch": "both",
      "start": 0,
      "count": 10,
      "precreate": 10,
      "out_dir": "./mass_exports/regtest/tr/a0",
      "format": "csv,jsonl",
      "xpub_file": "./mass_exports/xpubs/regtest/tr/a0.xpub"
    },
    {
      "type": "verify",
      "wallet": "lab_tr_a0",
      "xpub_file": "./mass_exports/xpubs/regtest/tr/a0.xpub",
      "network": "regtest",
      "witness": "tr",
      "branch": "receive",
      "start": 0,
      "count": 10,
      "compare_from_latest_gen": true
    },
    {
      "type": "verify",
      "wallet": "lab_tr_a0",
      "xpub_file": "./mass_exports/xpubs/regtest/tr/a0.xpub",
      "network": "regtest",
      "witness": "tr",
      "branch": "change",
      "start": 0,
      "count": 10,
      "compare_from_latest_gen": true
    },
    {
      "type": "gen",
      "wallet": "lab_tr_a1",
      "network": "regtest",
      "witness": "tr",
      "account": 1,
      "branch": "both",
      "start": 0,
      "count": 5,
      "precreate": 5,
      "out_dir": "./mass_exports/regtest/tr/a1",
      "format": "csv,jsonl",
      "xpub_file": "./mass_exports/xpubs/regtest/tr/a1.xpub"
    },
    {
      "type": "verify",
      "wallet": "lab_tr_a1",
      "xpub_file": "./mass_exports/xpubs/regtest/tr/a1.xpub",
      "network": "regtest",
      "witness": "tr",
      "branch": "receive",
      "start": 0,
      "count": 5,
      "compare_from_latest_gen": true
    },
    {
      "type": "verify",
      "wallet": "lab_tr_a1",
      "xpub_file": "./mass_exports/xpubs/regtest/tr/a1.xpub",
      "network": "regtest",
      "witness": "tr",
      "branch": "change",
      "start": 0,
      "count": 5,
      "compare_from_latest_gen": true
    }
  ]
}
